{"index.md":"040d12aa","pages_base_css_index.md":"03f4e6df","pages_base_cssanimation_index.md":"4fe0e1c5","pages_base_html_index.md":"d03f3204","pages_base_js_index.md":"05a9409e","pages_base_uploadfile.md":"5a8a5166","pages_canvas_demo.md":"c6f43fb8","pages_canvas_index.md":"1a63c5d0","pages_css_note.md":"92f3fb9c","pages_git_githubquestion_index.md":"7dabf625","pages_index_index.md":"063b77d7","pages_interviews_browser.md":"9dbe9b5e","pages_interviews_css.md":"fc2607c2","pages_interviews_eventloop.md":"80e69939","pages_interviews_git.md":"5b867c54","pages_interviews_handwritefn.md":"4e261d89","pages_interviews_html.md":"a098a16d","pages_interviews_http.md":"57563dcc","pages_interviews_js.md":"ffb9855d","pages_interviews_networkrotocols.md":"c1c3676c","pages_interviews_vue.md":"ab49ea23","pages_interviews_webpack.md":"a5d49c11","pages_node_index.md":"41f511fe","pages_toolfun_download.md":"00eecb20","pages_toolfun_filetool.md":"949ce35e","pages_toolfun_imgtool.md":"e94166c4","pages_toolfun_timetool.md":"b85653c5","pages_uniapp_calendar.md":"584530fa","pages_uniapp_components-uploadimg.md":"27deed14","pages_uniapp_index.md":"c215cad1","pages_vite_index.md":"3a9f9879","pages_vite_vitepress.md":"529acb11","pages_vscodetool_index.md":"1bce1eaf","pages_vue3-element-admin_anxinpc.md":"3c3d956b","pages_vue3-element-admin_epcomponents.md":"bf718981","pages_vue3_basic_computed.md":"8fdb2f15","pages_vue3_basic_note.md":"2ee81a91","pages_vue3_basic_reactive.md":"2807db53","pages_vue3_basic_ref.md":"1c662a80","pages_vue3_basic_v-model.md":"b6a4c066","pages_vue3_components_componentnote.md":"ed8f1782","pages_vue3_components_provide.md":"7139fc37","pages_vue3_components_reg.md":"85bbe59f","pages_vue3_components_slot.md":"8052e582","pages_vue3treasures_vuecommontips.md":"2eda79a7","pages_vue3treasures_vuecomponents.md":"401d40ed","pages_vue3treasures_vuedirectives.md":"5c659af6","pages_vuecore_responsiveprinciples.md":"580f163b","pages_vuecore_virtualdom.md":"7fb4a0f1"}
